jenkins_job.py
jenkins_logs_parser.py
project_handlers/__init__.py
project_handlers/jenkins_handler.py
jenkins_handler-1.1.0.2.dist-info/METADATA
jenkins_handler-1.1.0.2.dist-info/WHEEL
jenkins_handler-1.1.0.2.dist-info/top_level.txt
jenkins_handler-1.1.0.2.dist-info/RECORD
