Metadata-Version: 2.1
Name: jenkins-handler
Version: 1.1.0.2
Summary: A Wrapper for Jenkins API
Home-page: UNKNOWN
Author: Deep Instinct
Author-email: tomerco@deepinstinct.com
License: UNKNOWN
Platform: UNKNOWN
Classifier: Programming Language :: Python :: 3
Classifier: License :: OSI Approved :: MIT License
Classifier: Operating System :: OS Independent
Requires-Dist: infra-common
Requires-Dist: python-jenkins
